CHANGES.txt
INSTALL.txt
LICENSE.txt
MANIFEST.in
README.txt
setup.py
bin/netgrep
docs/TODO.txt
netgrep/__init__.py
netgrep/async_dns.py
netgrep/feedfilter.py
netgrep.egg-info/PKG-INFO
netgrep.egg-info/SOURCES.txt
netgrep.egg-info/dependency_links.txt
netgrep.egg-info/requires.txt
netgrep.egg-info/top_level.txt