Metadata-Version: 1.0
Name: netgrep
Version: 0.3.6
Summary: Grep-like filter for files based on country codes and ASN
Home-page: http://pypi.python.org/pypi/netgrep/
Author: CSIRT Foundry / Chris Horsley
Author-email: chris.horsley@csirtfoundry.com
License: LICENSE.txt
Download-URL: https://github.com/csirtfoundry/netgrep/tarball/master
Platform: UNKNOWN
